Kuat/__init__.py
arifudin_gank-0.1.0.dist-info/METADATA
arifudin_gank-0.1.0.dist-info/WHEEL
arifudin_gank-0.1.0.dist-info/top_level.txt
arifudin_gank-0.1.0.dist-info/RECORD
